{
  "reflect": [
    {
      "name": "tech.kayys.gollek.spi.inference.InferenceRequest",
      "allDeclaredConstructors": true,
      "allPublicConstructors": true,
      "allDeclaredMethods": true,
      "allPublicMethods": true,
      "allDeclaredFields": true,
      "allPublicFields": true
    },
    {
      "name": "tech.kayys.gollek.spi.inference.InferenceResponse",
      "allDeclaredConstructors": true,
      "allPublicConstructors": true,
      "allDeclaredMethods": true,
      "allPublicMethods": true,
      "allDeclaredFields": true,
      "allPublicFields": true
    },
    {
      "name": "tech.kayys.gollek.spi.inference.InferenceParameters",
      "allDeclaredConstructors": true,
      "allPublicConstructors": true,
      "allDeclaredMethods": true,
      "allPublicMethods": true,
      "allDeclaredFields": true,
      "allPublicFields": true
    },
    {
      "name": "tech.kayys.gollek.spi.Message",
      "allDeclaredConstructors": true,
      "allPublicConstructors": true,
      "allDeclaredMethods": true,
      "allPublicMethods": true,
      "allDeclaredFields": true,
      "allPublicFields": true
    },
    {
      "name": "tech.kayys.gollek.spi.context.RequestContext",
      "allDeclaredConstructors": true,
      "allPublicConstructors": true,
      "allDeclaredMethods": true,
      "allPublicMethods": true,
      "allDeclaredFields": true,
      "allPublicFields": true
    },
    {
      "name": "tech.kayys.gollek.spi.execution.ExecutionContext",
      "allDeclaredConstructors": true,
      "allPublicConstructors": true,
      "allDeclaredMethods": true,
      "allPublicMethods": true,
      "allDeclaredFields": true,
      "allPublicFields": true
    },
    {
      "name": "tech.kayys.gollek.spi.execution.ExecutionToken",
      "allDeclaredConstructors": true,
      "allPublicConstructors": true,
      "allDeclaredMethods": true,
      "allPublicMethods": true,
      "allDeclaredFields": true,
      "allPublicFields": true
    },
    {
      "name": "tech.kayys.gollek.spi.provider.ProviderConfig",
      "allDeclaredConstructors": true,
      "allPublicConstructors": true,
      "allDeclaredMethods": true,
      "allPublicMethods": true,
      "allDeclaredFields": true,
      "allPublicFields": true
    },
    {
      "name": "tech.kayys.gollek.spi.provider.ProviderRequest",
      "allDeclaredConstructors": true,
      "allPublicConstructors": true,
      "allDeclaredMethods": true,
      "allPublicMethods": true,
      "allDeclaredFields": true,
      "allPublicFields": true
    },
    {
      "name": "tech.kayys.gollek.spi.provider.ProviderResponse",
      "allDeclaredConstructors": true,
      "allPublicConstructors": true,
      "allDeclaredMethods": true,
      "allPublicMethods": true,
      "allDeclaredFields": true,
      "allPublicFields": true
    },
    {
      "name": "tech.kayys.gollek.error.ErrorPayload",
      "allDeclaredConstructors": true,
      "allPublicConstructors": true,
      "allDeclaredMethods": true,
      "allPublicMethods": true,
      "allDeclaredFields": true,
      "allPublicFields": true
    },
    {
      "name": "tech.kayys.gollek.spi.observability.AuditPayload",
      "allDeclaredConstructors": true,
      "allPublicConstructors": true,
      "allDeclaredMethods": true,
      "allPublicMethods": true,
      "allDeclaredFields": true,
      "allPublicFields": true
    },
    {
      "name": "tech.kayys.gollek.spi.plugin.PluginState",
      "allDeclaredConstructors": true,
      "allPublicConstructors": true,
      "allDeclaredMethods": true,
      "allPublicMethods": true,
      "allDeclaredFields": true,
      "allPublicFields": true
    },
    {
      "name": "tech.kayys.gollek.spi.model.DeviceType",
      "allDeclaredConstructors": true,
      "allPublicConstructors": true,
      "allDeclaredMethods": true,
      "allPublicMethods": true,
      "allDeclaredFields": true,
      "allPublicFields": true
    },
    {
      "name": "io.smallrye.mutiny.Uni",
      "allDeclaredConstructors": true,
      "allPublicConstructors": true,
      "allDeclaredMethods": true,
      "allPublicMethods": true
    },
    {
      "name": "io.smallrye.mutiny.Multi",
      "allDeclaredConstructors": true,
      "allPublicConstructors": true,
      "allDeclaredMethods": true,
      "allPublicMethods": true
    },
    {
      "name": "com.fasterxml.jackson.databind.ObjectMapper",
      "allDeclaredConstructors": true,
      "allPublicConstructors": true,
      "allDeclaredMethods": true,
      "allPublicMethods": true
    },
    {
      "name": "com.fasterxml.jackson.databind.JsonNode",
      "allDeclaredConstructors": true,
      "allPublicConstructors": true,
      "allDeclaredMethods": true,
      "allPublicMethods": true
    },
    {
      "name": "java.util.Optional",
      "allDeclaredConstructors": true,
      "allPublicConstructors": true,
      "allDeclaredMethods": true,
      "allPublicMethods": true
    }
  ],
  "jni": [],
  "proxy": [],
  "resources": [
    {
      "pattern": "META-INF/services/.*"
    },
    {
      "pattern": "application\\.properties"
    },
    {
      "pattern": "application\\.yml"
    },
    {
      "pattern": "application\\.yaml"
    }
  ],
  "bundles": []
}
